setuptools_qt_py/__init__.py
setuptools_qt_py/py.typed
setuptools_qt_py-1.0.0.dist-info/licenses/LICENSE.rst
setuptools_qt_py-1.0.0.dist-info/METADATA
setuptools_qt_py-1.0.0.dist-info/WHEEL
setuptools_qt_py-1.0.0.dist-info/entry_points.txt
setuptools_qt_py-1.0.0.dist-info/top_level.txt
setuptools_qt_py-1.0.0.dist-info/zip-safe
setuptools_qt_py-1.0.0.dist-info/RECORD
