Metadata-Version: 2.4
Name: setuptools-qt.py
Version: 1.0.0
Summary: A setuptools plugin for converting Qt .ui and .qrc files to Python files with Qt.py.
Home-page: https://github.com/AWhetter/setuptools-qt.py
Author: Ashley Whetter
Author-email: ashley@awhetter.co.uk
License: MIT
Classifier: Development Status :: 5 - Production/Stable
Classifier: Intended Audience :: Developers
Classifier: License :: OSI Approved :: MIT License
Classifier: Programming Language :: Python :: 3
Classifier: Programming Language :: Python :: 3.7
Classifier: Programming Language :: Python :: 3.8
Classifier: Programming Language :: Python :: 3.9
Classifier: Programming Language :: Python :: 3.10
Classifier: Operating System :: POSIX
Classifier: Operating System :: MacOS :: MacOS X
Classifier: Operating System :: Microsoft :: Windows
Requires-Python: >=3.7
License-File: LICENSE.rst
Requires-Dist: PySide2>=5.14.0
Requires-Dist: Qt.py>=0.5.0
Requires-Dist: setuptools>=44.1
Requires-Dist: tomli; python_version < "3.11"
Dynamic: license-file
